{
  "quiz": [
    {
      "id": 736,
      "grammar_point_id": "ch16_01",
      "grammar_point": "~の",
      "question": "A「昨日、どうして来なかった（　　）？」B「ごめん、急に用事ができちゃって。」",
      "options": {
        "A": "の",
        "B": "か",
        "C": "かい",
        "D": "かね"
      },
      "answer": "A",
      "explanation": "句末的「の」加升调，表示疑问，语气比「か」柔和，常用于女性或儿童，或关系亲密的人之间。"
    },
    {
      "id": 737,
      "grammar_point_id": "ch16_01",
      "grammar_point": "~の",
      "question": "「さあ、早く寝る（　　）。明日も早いんだから。」",
      "options": {
        "A": "の",
        "B": "こと",
        "C": "もの",
        "D": "よう"
      },
      "answer": "A",
      "explanation": "句末的「の」读降调，可以表示轻微的、柔和的命令，常为女性对孩子使用。"
    },
    {
      "id": 738,
      "grammar_point_id": "ch16_01",
      "grammar_point": "~の",
      "question": "これは、私が作った（　　）。どうぞ、食べてみて。",
      "options": {
        "A": "の",
        "B": "こと",
        "C": "もの",
        "D": "わけ"
      },
      "answer": "A",
      "explanation": "句末的「の」读降调，表示轻微的断定或说明。句意为“这是我做的哦”。"
    },
    {
      "id": 739,
      "grammar_point_id": "ch16_01",
      "grammar_point": "~の",
      "question": "A「そのセーター、素敵ね。」B「ありがとう。母が編んでくれた（　　）。」",
      "options": {
        "A": "の",
        "B": "こと",
        "C": "もの",
        "D": "わけ"
      },
      "answer": "A",
      "explanation": "表示说明，“是妈妈给我织的”。"
    },
    {
      "id": 740,
      "grammar_point_id": "ch16_01",
      "grammar_point": "~の",
      "question": "A「今日のテスト、難しかった（　　）？」B「うん、すごく難しかったよ。」",
      "options": {
        "A": "の",
        "B": "か",
        "C": "かい",
        "D": "かね"
      },
      "answer": "A",
      "explanation": "表示柔和的疑问。“今天的考试难吗？”"
    },
    {
      "id": 741,
      "grammar_point_id": "ch16_02",
      "grammar_point": "~のだ/んだ",
      "question": "A「どうして遅れた（　　）？」B「すみません、電車が遅れたんです。」",
      "options": {
        "A": "んだ",
        "B": "のだ",
        "C": "のか",
        "D": "のか"
      },
      "answer": "C",
      "explanation": "「~んですか/のですか」用于询问原因或要求说明。句意为“为什么迟到了？”。回答时用「~んです/のです」来解释原因。"
    },
    {
      "id": 742,
      "grammar_point_id": "ch16_02",
      "grammar_point": "~のだ/んだ",
      "question": "なるほど、だから彼はあんなに怒っていた（　　）。",
      "options": {
        "A": "んだ",
        "B": "のだ",
        "C": "んだ",
        "D": "のだ"
      },
      "answer": "C",
      "explanation": "「~んだ/のだ」表示恍然大悟，明白了事情的缘由。句意为“原来如此，怪不得他那么生气啊”。"
    },
    {
      "id": 743,
      "grammar_point_id": "ch16_02",
      "grammar_point": "~のだ/んだ",
      "question": "A「頭が痛いんです。」B「そうですか。早く帰って休んだほうがいいですよ。薬を飲む（　　）？」",
      "options": {
        "A": "んですか",
        "B": "のですか",
        "C": "のですか",
        "D": "のですか"
      },
      "answer": "A",
      "explanation": "这题不适合用「~んですか」。应该是「薬は飲みましたか」（吃药了吗？）。如果硬要用，可以说「薬を飲むつもりなんですか」（你打算吃药吗？），但语境不符。"
    },
    {
      "id": 744,
      "grammar_point_id": "ch16_02",
      "grammar_point": "~のだ/んだ",
      "question": "この機械はどうやって使う（　　）か、教えてください。",
      "options": {
        "A": "んです",
        "B": "のです",
        "C": "んです",
        "D": "のです"
      },
      "answer": "C",
      "explanation": "「~んですか」用于要求对方说明。“请告诉我这台机器是怎么用的？”"
    },
    {
      "id": 745,
      "grammar_point_id": "ch16_02",
      "grammar_point": "~のだ/んだ",
      "question": "道がぬれている。昨夜、雨が降った（　　）。",
      "options": {
        "A": "んだ",
        "B": "のだ",
        "C": "んだ",
        "D": "のだ"
      },
      "answer": "D",
      "explanation": "表示根据“路面湿了”这个事实，做出“（看来）昨晚下雨了”的推断和解释。"
    },
    {
      "id": 746,
      "grammar_point_id": "ch16_03",
      "grammar_point": "~のに",
      "question": "このハサミは、紙を切る（　　）使うものです。",
      "options": {
        "A": "のに",
        "B": "ために",
        "C": "ように",
        "D": "ことで"
      },
      "answer": "A",
      "explanation": "「~のに」表示用途或目的，后项多为「使う」「必要だ」「便利だ」等词。句意为“这把剪刀是用来剪纸的”。"
    },
    {
      "id": 747,
      "grammar_point_id": "ch16_03",
      "grammar_point": "~のに",
      "question": "この辞書は、漢字を調べる（　　）とても便利だ。",
      "options": {
        "A": "のに",
        "B": "ために",
        "C": "ように",
        "D": "ことで"
      },
      "answer": "A",
      "explanation": "表示“在查汉字方面”很方便。"
    },
    {
      "id": 748,
      "grammar_point_id": "ch16_03",
      "grammar_point": "~のに",
      "question": "家を建てる（　　）、たくさんのお金がかかる。",
      "options": {
        "A": "のに",
        "B": "ために",
        "C": "ように",
        "D": "ことで"
      },
      "answer": "A",
      "explanation": "表示“在盖房子这件事上”需要花很多钱。"
    },
    {
      "id": 749,
      "grammar_point_id": "ch16_03",
      "grammar_point": "~のに",
      "question": "この道具は、釘を打つ（　　）必要です。",
      "options": {
        "A": "のに",
        "B": "ために",
        "C": "ように",
        "D": "ことで"
      },
      "answer": "A",
      "explanation": "表示“在钉钉子这件事上”是必要的。"
    },
    {
      "id": 750,
      "grammar_point_id": "ch16_03",
      "grammar_point": "~のに",
      "question": "駅まで行く（　　）、３０分ぐらいかかります。",
      "options": {
        "A": "のに",
        "B": "ために",
        "C": "ように",
        "D": "ことで"
      },
      "answer": "A",
      "explanation": "表示“去车站这件事”大约需要30分钟。"
    },
    {
      "id": 751,
      "grammar_point_id": "ch16_04",
      "grammar_point": "~ば",
      "question": "お金があれ（　　）、何でも買えるわけではない。",
      "options": {
        "A": "ば",
        "B": "たら",
        "C": "なら",
        "D": "と"
      },
      "answer": "A",
      "explanation": "「~ば」表示假定条件。动词「ある」的ば形是「あれば」。句意为“如果有钱的话，也并非什么都能买到”。"
    },
    {
      "id": 752,
      "grammar_point_id": "ch16_04",
      "grammar_point": "~ば",
      "question": "安けれ（　　）買うのだが、高すぎて手が出ない。",
      "options": {
        "A": "ば",
        "B": "たら",
        "C": "なら",
        "D": "と"
      },
      "answer": "A",
      "explanation": "い形容词的假定形是词干+「ければ」。「安い」→「安ければ」。句意为“如果便宜的话我就会买，但太贵了买不起”。"
    },
    {
      "id": 753,
      "grammar_point_id": "ch16_04",
      "grammar_point": "~ば",
      "question": "この薬を飲め（　　）、きっとよくなります。",
      "options": {
        "A": "ば",
        "B": "たら",
        "C": "なら",
        "D": "と"
      },
      "answer": "A",
      "explanation": "一类动词的假定形是词尾う段变え段+「ば」。「飲む」→「飲めば」。"
    },
    {
      "id": 754,
      "grammar_point_id": "ch16_04",
      "grammar_point": "~ば",
      "question": "静か（　　）、もっと勉強に集中できるのに。",
      "options": {
        "A": "ならば",
        "B": "であれば",
        "C": "なら",
        "D": "だったら"
      },
      "answer": "C",
      "explanation": "な形容词的假定形是词干+「なら」或「であれば」。选项C「なら」最简洁。"
    },
    {
      "id": 755,
      "grammar_point_id": "ch16_04",
      "grammar_point": "~ば",
      "question": "彼に会え（　　）、この手紙を渡してください。",
      "options": {
        "A": "ば",
        "B": "たら",
        "C": "なら",
        "D": "と"
      },
      "answer": "B",
      "explanation": "辨析题。当后项是表示请求、命令、意志的句子时，通常不用「~ば」，而用「~たら」。句意为“如果你见到他，请把这封信交给他”。所以B「会えたら」最合适。"
    },
    {
      "id": 756,
      "grammar_point_id": "ch16_05",
      "grammar_point": "~ばかり",
      "question": "遊んで（　　）いないで、少しは勉強しなさい。",
      "options": {
        "A": "ばかり",
        "B": "だけ",
        "C": "しか",
        "D": "のみ"
      },
      "answer": "A",
      "explanation": "「~てばかりいる」是固定句型，表示“光是...，总是...”，带有责备或不满的语气。句意为“别老是玩，也学学习啊”。"
    },
    {
      "id": 757,
      "grammar_point_id": "ch16_05",
      "grammar_point": "~ばかり",
      "question": "彼は、お酒（　　）飲んでいる。",
      "options": {
        "A": "ばかり",
        "B": "だけ",
        "C": "しか",
        "D": "のみ"
      },
      "answer": "A",
      "explanation": "表示“光喝酒”，强调行为的单一性，并含有“不喝点别的吗”的消极评价。"
    },
    {
      "id": 758,
      "grammar_point_id": "ch16_05",
      "grammar_point": "~ばかり",
      "question": "文句（　　）言っていないで、何か行動したらどうですか。",
      "options": {
        "A": "ばかり",
        "B": "だけ",
        "C": "しか",
        "D": "のみ"
      },
      "answer": "A",
      "explanation": "表示“别光是抱怨”。"
    },
    {
      "id": 759,
      "grammar_point_id": "ch16_05",
      "grammar_point": "~ばかり",
      "question": "あの二人は、会えばけんか（　　）している。",
      "options": {
        "A": "ばかり",
        "B": "だけ",
        "C": "しか",
        "D": "のみ"
      },
      "answer": "A",
      "explanation": "表示“一见面就吵架”，强调这种行为的频繁和单一。"
    },
    {
      "id": 760,
      "grammar_point_id": "ch16_05",
      "grammar_point": "~ばかり",
      "question": "甘いもの（　　）食べていると、虫歯になりますよ。",
      "options": {
        "A": "ばかり",
        "B": "だけ",
        "C": "しか",
        "D": "のみ"
      },
      "answer": "A",
      "explanation": "表示“光吃甜食的话...”。"
    },
    {
      "id": 761,
      "grammar_point_id": "ch16_06",
      "grammar_point": "~ばかりだ",
      "question": "準備はすべて終わった。あとは出発する（　　）。",
      "options": {
        "A": "ばかりだ",
        "B": "一方だ",
        "C": "ところだ",
        "D": "ものだ"
      },
      "answer": "A",
      "explanation": "「動詞辞書形+ばかりだ」的另一种用法，表示“只剩下...了，只等...了”。句意为“准备工作全部完成，只等出发了”。"
    },
    {
      "id": 762,
      "grammar_point_id": "ch16_06",
      "grammar_point": "~ばかりだ",
      "question": "円高が進み、輸出企業の経営は悪化する（　　）。",
      "options": {
        "A": "ばかりだ",
        "B": "一方だ",
        "C": "ところだ",
        "D": "ものだ"
      },
      "answer": "A",
      "explanation": "「~ばかりだ」表示事态朝着不好的方向发展，与「一方だ」类似。句意为“日元不断升值，出口企业的经营状况不断恶化”。"
    },
    {
      "id": 763,
      "grammar_point_id": "ch16_06",
      "grammar_point": "~ばかりだ",
      "question": "手術後の祖父の病状は、回復に向かう（　　）。",
      "options": {
        "A": "ばかりだ",
        "B": "一方だ",
        "C": "ところだ",
        "D": "ものだ"
      },
      "answer": "B",
      "explanation": "辨析题。「~ばかりだ」多用于不好的事态，而「一方だ」既可用于好的事态，也可用于不好的事态。“病情正在恢复”是好事，所以用「一方だ」更合适。"
    },
    {
      "id": 764,
      "grammar_point_id": "ch16_06",
      "grammar_point": "~ばかりだ",
      "question": "状況は、悪くなる（　　）。",
      "options": {
        "A": "ばかりだ",
        "B": "一方だ",
        "C": "ところだ",
        "D": "ものだ"
      },
      "answer": "A",
      "explanation": "表示“情况不断恶化”。A和B都可以，但A更能强调消极的语感。"
    },
    {
      "id": 765,
      "grammar_point_id": "ch16_06",
      "grammar_point": "~ばかりだ",
      "question": "料理もできたし、飲み物も冷えている。さあ、お客さんが来るのを待つ（　　）。",
      "options": {
        "A": "ばかりだ",
        "B": "一方だ",
        "C": "ところだ",
        "D": "ものだ"
      },
      "answer": "A",
      "explanation": "表示“只等客人来了”。"
    },
    {
      "id": 766,
      "grammar_point_id": "ch16_07",
      "grammar_point": "~はずだ/はずがない",
      "question": "彼は昨日、日本に来たばかりだから、日本語が上手な（　　）。",
      "options": {
        "A": "はずがない",
        "B": "わけがない",
        "C": "ことはない",
        "D": "ものではない"
      },
      "answer": "A",
      "explanation": "「~はずがない」表示强烈的否定推断，“理应不会...，不可能...”。句意为“他昨天才刚到日本，日语理应不会很好”。选项B意思相同。"
    },
    {
      "id": 767,
      "grammar_point_id": "ch16_07",
      "grammar_point": "~はずだ/はずがない",
      "question": "地図のとおりに来たのだから、道に迷う（　　）。",
      "options": {
        "A": "はずはない",
        "B": "わけはない",
        "C": "ことはない",
        "D": "ものではない"
      },
      "answer": "A",
      "explanation": "表示“因为是照着地图来的，所以理应不会迷路”。"
    },
    {
      "id": 768,
      "grammar_point_id": "ch16_07",
      "grammar_point": "~はずだ/はずがない",
      "question": "あれ、おかしいな。ここに置いておいた（　　）なのに、鍵がない。",
      "options": {
        "A": "はず",
        "B": "わけ",
        "C": "こと",
        "D": "もの"
      },
      "answer": "A",
      "explanation": "表示与自己预想或常理不符的情况。“咦，真奇怪。我理应是放在这里的，钥匙却不见了”。"
    },
    {
      "id": 769,
      "grammar_point_id": "ch16_07",
      "grammar_point": "~はずだ/はずがない",
      "question": "彼はまじめな学生だから、無断で休む（　　）。",
      "options": {
        "A": "はずがない",
        "B": "わけがない",
        "C": "ことはない",
        "D": "ものではない"
      },
      "answer": "A",
      "explanation": "表示“因为他是认真的学生，所以不可能无故缺席”。"
    },
    {
      "id": 770,
      "grammar_point_id": "ch16_07",
      "grammar_point": "~はずだ/はずがない",
      "question": "ちゃんと約束した（　　）だから、彼はきっと来るよ。",
      "options": {
        "A": "はず",
        "B": "わけ",
        "C": "こと",
        "D": "もの"
      },
      "answer": "A",
      "explanation": "「~はずだ」表示基于事实的有把握的推断。“因为好好约好了，所以他肯定会来的”。"
    },
    {
      "id": 771,
      "grammar_point_id": "ch16_08",
      "grammar_point": "~ば~ほど",
      "question": "この本は、読め（　　）読む（　　）、面白くなる。",
      "options": {
        "A": "ば、ほど",
        "B": "たら、だけ",
        "C": "なら、ぐらい",
        "D": "と、くらい"
      },
      "answer": "A",
      "explanation": "「~ば~ほど」是固定句型，表示“越...越...”。句意为“这本书越读越有趣”。"
    },
    {
      "id": 772,
      "grammar_point_id": "ch16_08",
      "grammar_point": "~ば~ほど",
      "question": "パソコンは、値段が高けれ（　　）高い（　　）、性能もいいとは限らない。",
      "options": {
        "A": "ば、ほど",
        "B": "たら、だけ",
        "C": "なら、ぐらい",
        "D": "と、くらい"
      },
      "answer": "A",
      "explanation": "い形容词的用法，「高ければ高いほど」。句意为“电脑并非价格越高性能就越好”。"
    },
    {
      "id": 773,
      "grammar_point_id": "ch16_08",
      "grammar_point": "~ば~ほど",
      "question": "操作が簡単（　　）簡単な（　　）、お年寄りにも使いやすい。",
      "options": {
        "A": "ならば、ほど",
        "B": "であれば、だけ",
        "C": "なら、ほど",
        "D": "だったら、ぐらい"
      },
      "answer": "C",
      "explanation": "な形容词的用法，「簡単なら簡単なほど」。句意为“操作越简单，对老年人来说也越好用”。"
    },
    {
      "id": 774,
      "grammar_point_id": "ch16_08",
      "grammar_point": "~ば~ほど",
      "question": "考えれ（　　）考える（　　）、わからなくなってきた。",
      "options": {
        "A": "ば、ほど",
        "B": "たら、だけ",
        "C": "なら、ぐらい",
        "D": "と、くらい"
      },
      "answer": "A",
      "explanation": "动词的用法，「考えれば考えるほど」。"
    },
    {
      "id": 775,
      "grammar_point_id": "ch16_08",
      "grammar_point": "~ば~ほど",
      "question": "優れた人（　　）優れた人（　　）、謙虚なものだ。",
      "options": {
        "A": "ならば、ほど",
        "B": "であれば、だけ",
        "C": "なら、ほど",
        "D": "だったら、ぐらい"
      },
      "answer": "C",
      "explanation": "名词的用法，「優れた人なら優れた人ほど」。句意为“越是优秀的人，越是谦虚”。"
    },
    {
      "id": 776,
      "grammar_point_id": "ch16_09",
      "grammar_point": "~ぶり",
      "question": "彼とは、高校を卒業して以来、１０年（　　）に再会した。",
      "options": {
        "A": "ぶり",
        "B": "ばかり",
        "C": "きり",
        "D": "ほど"
      },
      "answer": "A",
      "explanation": "「~ぶり」接在表示时间的词后，表示“时隔...”。句意为“我和他自高中毕业后，时隔10年才重逢”。"
    },
    {
      "id": 777,
      "grammar_point_id": "ch16_09",
      "grammar_point": "~ぶり",
      "question": "久し（　　）に故郷に帰った。",
      "options": {
        "A": "ぶり",
        "B": "ばかり",
        "C": "きり",
        "D": "ほど"
      },
      "answer": "A",
      "explanation": "「久しぶり」是固定搭配，意为“好久不见，时隔很久”。"
    },
    {
      "id": 778,
      "grammar_point_id": "ch16_09",
      "grammar_point": "~ぶり",
      "question": "彼の堂々とした話し（　　）は、とても頼もしい。",
      "options": {
        "A": "ぶり",
        "B": "かた",
        "C": "よう",
        "D": "ふう"
      },
      "answer": "A",
      "explanation": "「~ぶり」接在动词ます形后，表示“...的样子/状态”。「話しぶり」意为“说话的样子”。"
    },
    {
      "id": 779,
      "grammar_point_id": "ch16_09",
      "grammar_point": "~ぶり",
      "question": "雨は、３日（　　）にやっとやんだ。",
      "options": {
        "A": "ぶり",
        "B": "ばかり",
        "C": "きり",
        "D": "ほど"
      },
      "answer": "A",
      "explanation": "表示“时隔3天，雨终于停了”。"
    },
    {
      "id": 780,
      "grammar_point_id": "ch16_09",
      "grammar_point": "~ぶり",
      "question": "彼女の仕事（　　）には、いつも感心させられる。",
      "options": {
        "A": "ぶり",
        "B": "かた",
        "C": "よう",
        "D": "ふう"
      },
      "answer": "A",
      "explanation": "「仕事ぶり」表示“工作的状态/样子”。"
    },
    {
      "id": 781,
      "grammar_point_id": "ch16_10",
      "grammar_point": "~べきだ/べきではない",
      "question": "学生は、もっと本を読む（　　）。",
      "options": {
        "A": "べきだ",
        "B": "はずだ",
        "C": "わけだ",
        "D": "ものだ"
      },
      "answer": "A",
      "explanation": "「~べきだ」表示“应该...”，从道理、常识上认为有必要这样做。句意为“学生应该多读书”。"
    },
    {
      "id": 782,
      "grammar_point_id": "ch16_10",
      "grammar_point": "~べきだ/べきではない",
      "question": "人の悪口は、言う（　　）。",
      "options": {
        "A": "べきではない",
        "B": "はずがない",
        "C": "わけではない",
        "D": "ものではない"
      },
      "answer": "A",
      "explanation": "「~べきではない」表示“不应该...”。句意为“不应该说别人的坏话”。"
    },
    {
      "id": 783,
      "grammar_point_id": "ch16_10",
      "grammar_point": "~べきだ/べきではない",
      "question": "どんなに小さな約束でも、守る（　　）だ。",
      "options": {
        "A": "べき",
        "B": "はず",
        "C": "わけ",
        "D": "もの"
      },
      "answer": "A",
      "explanation": "表示“应该遵守”。"
    },
    {
      "id": 784,
      "grammar_point_id": "ch16_10",
      "grammar_point": "~べきだ/べきではない",
      "question": "彼のしたことは、決して許される（　　）ことではない。",
      "options": {
        "A": "べき",
        "B": "はずの",
        "C": "わけの",
        "D": "ものの"
      },
      "answer": "A",
      "explanation": "「許されるべきことではない」意为“是不应该被原谅的事”。"
    },
    {
      "id": 785,
      "grammar_point_id": "ch16_10",
      "grammar_point": "~べきだ/べきではない",
      "question": "もっと早く相談す（　　）だったと後悔している。",
      "options": {
        "A": "べき",
        "B": "るべき",
        "C": "べき",
        "D": "べき"
      },
      "answer": "A",
      "explanation": "「~べきだった」是「~べきだ」的过去时，表示“本应该...（但没做）”，含有后悔的语气。三类动词「する」接「べきだ」时，可以说「するべきだ」或「すべきだ」。"
    }
  ]
}